{"job_id": "81fe086e-f396-4dfe-a2b6-38cde2c37d5b", "status": "success", "started_at": "2026-05-05T17:19:24.251323+00:00", "completed_at": "2026-05-05T17:19:26.125022+00:00", "logs": [{"ts": "2026-05-05T17:19:24.251323+00:00", "message": "Detection job queued"}, {"ts": "2026-05-05T17:19:24.257325+00:00", "message": "Anomaly detection job started"}, {"ts": "2026-05-05T17:19:24.307345+00:00", "message": "Resolved params service=all range=2025-09-24..2025-10-25"}, {"ts": "2026-05-05T17:19:25.149050+00:00", "message": "Daily metrics loaded (32 rows)"}, {"ts": "2026-05-05T17:19:25.151054+00:00", "message": "processing metric=dau"}, {"ts": "2026-05-05T17:19:25.391066+00:00", "message": "metric done=dau"}, {"ts": "2026-05-05T17:19:25.392055+00:00", "message": "processing metric=churn_rate"}, {"ts": "2026-05-05T17:19:25.630048+00:00", "message": "metric done=churn_rate"}, {"ts": "2026-05-05T17:19:25.632027+00:00", "message": "processing metric=revenue"}, {"ts": "2026-05-05T17:19:25.880028+00:00", "message": "metric done=revenue"}, {"ts": "2026-05-05T17:19:25.882022+00:00", "message": "processing metric=renewals"}, {"ts": "2026-05-05T17:19:26.123029+00:00", "message": "metric done=renewals"}, {"ts": "2026-05-05T17:19:26.124024+00:00", "message": "Detection completed in 1867ms"}], "result": {"detection_run_id": "81fe086e-f396-4dfe-a2b6-38cde2c37d5b", "total_anomalies": 8, "critical": 7, "high": 0, "medium": 1, "run_completed_at": "2026-05-05T17:19:26.125022+00:00"}, "error": null, "request": {"start_date": null, "end_date": null, "service_id": null, "metrics": ["dau", "churn_rate", "revenue", "renewals"], "severity": ["critical", "high", "medium"]}}